micropytimer/__init__.py
micropytimer/micropytimer.py
micropytimer-1.0.0.dist-info/METADATA
micropytimer-1.0.0.dist-info/WHEEL
micropytimer-1.0.0.dist-info/licenses/LICENSE
micropytimer-1.0.0.dist-info/RECORD
