Metadata-Version: 2.4
Name: micropytimer
Version: 1.0.0
Summary: Micropython friendly library to create timers that trigger functions
Project-URL: Homepage, https://github.com/goodeb/micropytimer
Project-URL: Issues, https://github.com/goodeb/micropytimer/issues
Author-email: Brent Goode <brent.goode@gmail.com>
License-Expression: MIT
License-File: LICENSE
Classifier: Operating System :: OS Independent
Classifier: Programming Language :: Python :: 3
Requires-Python: >=3.9
